Metadata-Version: 1.0
Name: boyfriend
Version: 0.2
Summary: Boyfriend package for fun
Home-page: https://github.com/arthurc0102/boyfriend
Author: Arthur Chang
Author-email: arthurc0102@gmail.com
License: MIT
Platform: UNKNOWN
